{
  "title": "文档摘要报告",
  "key_points": [
    {
      "point": "计算机使用补码表示法以简化硬件设计，支持用相同电路处理正负数加法，避免减法专用电路和正负零歧义问题。",
      "evidence": [
        1
      ]
    },
    {
      "point": "浮点数（float）采用IEEE 754标准编码，通过特殊表示方式实现比整数更大的取值范围，尽管其位长与int相同。",
      "evidence": [
        1
      ]
    },
    {
      "point": "双向队列兼具栈和队列特性，可用于实现栈的先入后出逻辑（如撤销功能），同时支持在队首删除以限制历史记录长度。",
      "evidence": [
        2
      ]
    },
    {
      "point": "算法是在有限时间内解决特定问题的一组明确指令，具有明确输入输出、可行性、确定性等特性。",
      "evidence": [
        4
      ]
    },
    {
      "point": "数据结构是组织和存储数据的方式，与算法共同构成计算机解决问题的基础。",
      "evidence": [
        4
      ]
    },
    {
      "point": "递归的执行机制与栈的先入后出原则一致，调用栈通过栈帧管理函数调用与返回，可被显式栈模拟为迭代形式。",
      "evidence": [
        5
      ]
    }
  ],
  "analysis": "所有证据均来自同一本书的章节，聚焦于数据结构与算法的基础概念。证据[1]说明计算机底层数据表示（补码、浮点数）如何影响运算效率；证据[2]和[5]分别展示栈和双向队列在逻辑实现中的作用，强调栈作为递归和撤销功能的核心支撑结构；证据[4]定义了算法与数据结构的基本概念，构成全书理论基础。整体主线是：从底层数据表示（[1]）到抽象数据结构（[2][5]），再到算法定义（[4]），形成由硬件到软件、由实现到理论的递进关系。",
  "analysis_evidence": [
    1,
    2,
    4,
    5
  ],
  "conclusion": "文档系统介绍了计算机底层数据表示、核心数据结构（栈、双向队列）及算法基本定义，强调栈在递归和撤销机制中的关键作用，但未涉及Transformer的任何结构或机制。",
  "conclusion_evidence": [
    1,
    2,
    4,
    5
  ]
}